py_cwru/__init__.py
py_cwru-1.0.2.dist-info/METADATA
py_cwru-1.0.2.dist-info/WHEEL
py_cwru-1.0.2.dist-info/entry_points.txt
py_cwru-1.0.2.dist-info/top_level.txt
py_cwru-1.0.2.dist-info/RECORD
