Metadata-Version: 2.1
Name: py-cwru
Version: 1.0.2
Summary: README.md
Home-page: UNKNOWN
Author: Xu Fangzheng
Author-email: fonderxu@163.com
License: UNKNOWN
Platform: UNKNOWN
